odoo/addons/pos_cash_control_override/README.rst
odoo/addons/pos_cash_control_override/__init__.py
odoo/addons/pos_cash_control_override/__manifest__.py
odoo/addons/pos_cash_control_override/i18n/it.po
odoo/addons/pos_cash_control_override/i18n/pos_cash_control_override.pot
odoo/addons/pos_cash_control_override/models/__init__.py
odoo/addons/pos_cash_control_override/models/account_bank_statement_line.py
odoo/addons/pos_cash_control_override/models/pos_session.py
odoo/addons/pos_cash_control_override/readme/CONTEXT.md
odoo/addons/pos_cash_control_override/readme/CONTRIBUTORS.md
odoo/addons/pos_cash_control_override/readme/DESCRIPTION.md
odoo/addons/pos_cash_control_override/readme/ROADMAP.md
odoo/addons/pos_cash_control_override/readme/USAGE.md
odoo/addons/pos_cash_control_override/static/description/icon.png
odoo/addons/pos_cash_control_override/static/description/index.html
odoo/addons/pos_cash_control_override/tests/__init__.py
odoo/addons/pos_cash_control_override/tests/test_frontend.py
odoo_addon_pos_cash_control_override-16.0.1.0.0.4.dist-info/METADATA
odoo_addon_pos_cash_control_override-16.0.1.0.0.4.dist-info/WHEEL
odoo_addon_pos_cash_control_override-16.0.1.0.0.4.dist-info/top_level.txt
odoo_addon_pos_cash_control_override-16.0.1.0.0.4.dist-info/RECORD
